optimal_LR/__init__.py
optimal_LR/optimized_lr.py
OptimizedLR-1.3.dist-info/METADATA
OptimizedLR-1.3.dist-info/WHEEL
OptimizedLR-1.3.dist-info/top_level.txt
OptimizedLR-1.3.dist-info/RECORD
